quantlib/__init__.py
quantlib/instruments/__init__.py
quantlib/main/__init__.py
quantlib/main/graph_plotter_strat.py
quantlib/main/option_selling_strat.py
quantlib/main/price_archiver_strat.py
nse_ab_quantlib-0.8.0.dist-info/LICENSE
nse_ab_quantlib-0.8.0.dist-info/METADATA
nse_ab_quantlib-0.8.0.dist-info/WHEEL
nse_ab_quantlib-0.8.0.dist-info/top_level.txt
nse_ab_quantlib-0.8.0.dist-info/RECORD
