Metadata-Version: 2.1
Name: nse-ab-quantlib
Version: 0.8.0
Summary: Way of Testing option selling strategies in NSE
Home-page: https://github.com/jaskirat1208/backtest-platform
Author: Jaskirat Singh
Author-email: jaskiratsingh1208@gmail.com
Classifier: Programming Language :: Python :: 3
Classifier: License :: OSI Approved :: MIT License
License-File: LICENSE
Requires-Dist: nsepython
Requires-Dist: smartapi-python
Requires-Dist: alphatools-jv
Requires-Dist: mintotp
Requires-Dist: websocket
Requires-Dist: twine
Requires-Dist: wheel
Requires-Dist: websocket-client
Requires-Dist: multipledispatch (~=0.6.0)
Requires-Dist: requests
Requires-Dist: pandas
Requires-Dist: setuptools
